{
    "imgs-hiss": [
      { "src": "../imgs-2/IMG-20240815-WA0005.jpg" },
      { "src": "../imgs-2/IMG-20240815-WA0007.jpg" },
      { "src": "../imgs-2/IMG-20240815-WA0009.jpg" },
      { "src": "../imgs-2/IMG-20240818-WA0002.jpg" },
      { "src": "../imgs-2/IMG-20240818-WA0006.jpg" },
      { "src": "../imgs-2/IMG-20240826-WA0001.jpg" },
      { "src": "../imgs-2/IMG-20240826-WA0002.jpg" },
      { "src": "../imgs-2/IMG-20240826-WA0003.jpg" },
      { "src": "../imgs-2/IMG-20240826-WA0004.jpg" },
      { "src": "../imgs-2/IMG-20240826-WA0005.jpg" },
      { "src": "../imgs-2/IMG-20240826-WA0006.jpg" },
      { "src": "../imgs-2/IMG-20240826-WA0007.jpg" },
      { "src": "../imgs-2/IMG-20240826-WA0008.jpg" },
      { "src": "../imgs-2/IMG-20240826-WA0009.jpg" },
      { "src": "../imgs-2/IMG-20240826-WA0010.jpg" },
      { "src": "../imgs-2/IMG-20240826-WA0011.jpg" },
      { "src": "../imgs-2/IMG-20240826-WA0012.jpg" },
      { "src": "../imgs-2/IMG-20240826-WA0013.jpg" },
      { "src": "../imgs-2/IMG-20240826-WA0014.jpg" },
      { "src": "../imgs-2/IMG-20240826-WA0015.jpg" },
      { "src": "../imgs-2/IMG-20240826-WA0016.jpg" },
      { "src": "../imgs-2/IMG-20240826-WA0017.jpg" },
      { "src": "../imgs-2/IMG-20240826-WA0018.jpg" },
      { "src": "../imgs-2/IMG-20240826-WA0019.jpg" },
      { "src": "../imgs-2/IMG-20240826-WA0020.jpg" },
      { "src": "../imgs-2/WhatsApp Image 2024-08-26 at 02.00.49_9e2d5dcc.jpg" },
      { "src": "../imgs-2/IMG-20240826-WA0021.jpg" },
      { "src": "../imgs-2/IMG-20240826-WA0033.jpg" },
      { "src": "../imgs-2/IMG-20240826-WA0022.jpg" },
      { "src": "../imgs-2/IMG-20240826-WA0023.jpg" },
      { "src": "../imgs-2/IMG-20240826-WA0024.jpg" },
      { "src": "../imgs-2/IMG-20240826-WA0025.jpg" },
      { "src": "../imgs-2/IMG-20240826-WA0026.jpg" },
      { "src": "../imgs-2/IMG-20240826-WA0027.jpg" },
      { "src": "../imgs-2/IMG-20240826-WA0028.jpg" },
      { "src": "../imgs-2/IMG-20240826-WA0029.jpg" },
      { "src": "../imgs-2/IMG-20240826-WA0030.jpg" },
      { "src": "../imgs-2/IMG-20240826-WA0031.jpg" },
      { "src": "../imgs-2/IMG-20240826-WA0032.jpg" },
      { "src": "../imgs-2/IMG-20240826-WA0034.jpg" },
      { "src": "../imgs-2/IMG-20240826-WA0035.jpg" },
      { "src": "../imgs-2/IMG-20240826-WA0036.jpg" },
      { "src": "../imgs-2/IMG-20240826-WA0037.jpg" },
      { "src": "../imgs-2/IMG-20240826-WA0038.jpg" },
      { "src": "../imgs-2/IMG-20240826-WA0039.jpg" },
      { "src": "../imgs-2/IMG-20240826-WA0040.jpg" },
      { "src": "../imgs-2/IMG-20240826-WA0041.jpg" },
      { "src": "../imgs-2/IMG-20240826-WA0042.jpg" },
      { "src": "../imgs-2/IMG-20240826-WA0043.jpg" },
      { "src": "../imgs-2/IMG-20240826-WA0045.jpg" },
      { "src": "../imgs-2/IMG-20240826-WA0046.jpg" },
      { "src": "../imgs-2/IMG-20240826-WA0047.jpg" },
      { "src": "../imgs-2/IMG-20240826-WA0048.jpg" },
      { "src": "../imgs-2/IMG-20240826-WA0049.jpg" },
      { "src": "../imgs-2/IMG-20240826-WA0050.jpg" },
      { "src": "../imgs-2/IMG-20240826-WA0051.jpg" },
      { "src": "../imgs-2/IMG-20240826-WA0052.jpg" },
      { "src": "../imgs-2/IMG-20240826-WA0053.jpg" },
      { "src": "../imgs-2/IMG-20240826-WA0054.jpg" },
      { "src": "../imgs-2/IMG-20240826-WA0055.jpg" },
      { "src": "../imgs-2/IMG-20240826-WA0056.jpg" },
      { "src": "../imgs-2/IMG-20240826-WA0057.jpg" },
      { "src": "../imgs-2/IMG-20240826-WA0059.jpg" },
      { "src": "../imgs-2/IMG-20240826-WA0060.jpg" },
      { "src": "../imgs-2/IMG-20240826-WA0061.jpg" },
      { "src": "../imgs-2/IMG-20240826-WA0062.jpg" },
      { "src": "../imgs-2/IMG-20240826-WA0063.jpg" },
      { "src": "../imgs-2/IMG-20240826-WA0064.jpg" },
      { "src": "../imgs-2/IMG-20240826-WA0065.jpg" },
      { "src": "../imgs-2/IMG-20240826-WA0066.jpg" },
      { "src": "../imgs-2/IMG-20240826-WA0067.jpg" },
      { "src": "../imgs-2/IMG-20240826-WA0068.jpg" },
      { "src": "../imgs-2/IMG-20240826-WA0069.jpg" },
      { "src": "../imgs-2/IMG-20240826-WA0070.jpg" },
      { "src": "../imgs-2/IMG-20240826-WA0071.jpg" },
      { "src": "../imgs-2/IMG-20240826-WA0074.jpg" },
      { "src": "../imgs-2/IMG-20240826-WA0075.jpg" },
      { "src": "../imgs-2/IMG-20240826-WA0076.jpg" },
      { "src": "../imgs-2/IMG-20240826-WA0077.jpg" },
      { "src": "../imgs-2/IMG-20240826-WA0078.jpg" },
      { "src": "../imgs-2/IMG-20240826-WA0079.jpg" },
      { "src": "../imgs-2/IMG-20240826-WA0080.jpg" },
      { "src": "../imgs-2/IMG-20240826-WA0081.jpg" },
      { "src": "../imgs-2/IMG-20240930-WA0016.jpg" },
      { "src": "../imgs-2/IMG-20240930-WA0009.jpg" },
      { "src": "../imgs-2/IMG-20240930-WA0010.jpg" },
      { "src": "../imgs-2/IMG-20240930-WA0011.jpg" },
      { "src": "../imgs-2/IMG-20240930-WA0012.jpg" },
      { "src": "../imgs-2/IMG-20240930-WA0013.jpg" },
      { "src": "../imgs-2/IMG-20240930-WA0014.jpg" },
      { "src": "../imgs-2/IMG-20240930-WA0015.jpg" },
      { "src": "../imgs-2/d7cd3246-7030-48f5-90e4-a67a97f1e5c2.jfif" },
      { "src": "../imgs-2/eab651d9-a20b-4d6e-b5ac-2dea165dad24 (1).jfif" }
    ]
  }
  